PyDCSL/__init__.py
PyDCSL/__main__.py
PyDCSL/modules/__init__.py
PyDCSL/modules/args_parser.py
PyDCSL/modules/banners.py
PyDCSL/modules/dcsl.py
PyDCSL/modules/logging.py
pydcsl-0.4.0.dist-info/entry_points.txt
pydcsl-0.4.0.dist-info/LICENSE
pydcsl-0.4.0.dist-info/METADATA
pydcsl-0.4.0.dist-info/WHEEL
pydcsl-0.4.0.dist-info/RECORD
