Metadata-Version: 2.3
Name: PyDCSL
Version: 0.4.0
Summary: A compact Python tool to check if a Widevine device certificate (DCSL) is revoked or valid.
License: MIT
Author: ThatNotEasy
Author-email: apid9755@gmail.me
Requires-Python: >=3.7
Classifier: License :: OSI Approved :: MIT License
Classifier: Operating System :: OS Independent
Classifier: Programming Language :: Python :: 3
Classifier: Programming Language :: Python :: 3.7
Classifier: Programming Language :: Python :: 3.8
Classifier: Programming Language :: Python :: 3.9
Classifier: Programming Language :: Python :: 3.10
Classifier: Programming Language :: Python :: 3.11
Classifier: Programming Language :: Python :: 3.12
Classifier: Programming Language :: Python :: 3.13
Requires-Dist: colorama
Requires-Dist: coloredlogs
Requires-Dist: requests
Project-URL: Homepage, https://github.com/ThatNotEasy/PyDCSL
